replutil/__init__.py
replutil/keepalive.py
replutil/util.py
replutil-0.1.1.dist-info/LICENSE
replutil-0.1.1.dist-info/WHEEL
replutil-0.1.1.dist-info/METADATA
replutil-0.1.1.dist-info/RECORD
