Metadata-Version: 2.1
Name: replutil
Version: 0.1.1
Summary: A collection of utilities for running services on repl.it
Home-page: https://github.com/regulad/replutil
License: GPLv3
Author: regulad
Author-email: regulad@regulad.xyz
Requires-Python: >=3.8,<4.0
Classifier: License :: Other/Proprietary License
Classifier: Programming Language :: Python :: 3
Classifier: Programming Language :: Python :: 3.8
Classifier: Programming Language :: Python :: 3.9
Requires-Dist: Flask (>=2.0.2,<3.0.0)
Requires-Dist: click (>=8.0.3,<9.0.0)
Requires-Dist: requests (>=2.27.1,<3.0.0)
Project-URL: Repository, https://github.com/regulad/replutil
